city/__init__.py
city/admin.py
city/apps.py
city/models.py
city/tests.py
city/views.py
django_city-0.0.4.dist-info/DESCRIPTION.rst
django_city-0.0.4.dist-info/METADATA
django_city-0.0.4.dist-info/RECORD
django_city-0.0.4.dist-info/WHEEL
django_city-0.0.4.dist-info/metadata.json
django_city-0.0.4.dist-info/top_level.txt
